{
  "gitSyncId": "687f301f740a4a3a037764bb_b7bf2343-4257-49c2-ab6b-0093045ad888",
  "id": "Mei.categorias_InsertQuery",
  "pluginId": "postgres-plugin",
  "pluginType": "DB",
  "unpublishedAction": {
    "actionConfiguration": {
      "body": "INSERT INTO mei.\"categorias\" (\n\t\"nome_categoria\",\n\t\"descricao\",\n\t\"ativo\")\nVALUES (\n\t'{{insert_form.formData.nome_categoria}}',\n\t'{{insert_form.formData.descricao}}',\n\t'{{insert_form.formData.ativo}}');",
      "encodeParamsToggle": true,
      "paginationType": "NONE",
      "pluginSpecifiedTemplates": [
        {
          "value": true
        }
      ],
      "timeoutInMillisecond": 10000
    },
    "confirmBeforeExecute": false,
    "datasource": {
      "id": "users",
      "isAutoGenerated": false,
      "name": "users",
      "pluginId": "postgres-plugin"
    },
    "dynamicBindingPathList": [
      {
        "key": "body"
      }
    ],
    "name": "InsertQuery",
    "pageId": "Mei.categorias",
    "runBehaviour": "MANUAL",
    "userSetOnLoad": false
  }
}